cellpyability/CellPyAbility.cppipe
cellpyability/__init__.py
cellpyability/cli.py
cellpyability/gda_analysis.py
cellpyability/simple_analysis.py
cellpyability/synergy_analysis.py
cellpyability/toolbox.py
cellpyability-0.1.0.dist-info/licenses/LICENSE.txt
cellpyability-0.1.0.dist-info/METADATA
cellpyability-0.1.0.dist-info/WHEEL
cellpyability-0.1.0.dist-info/entry_points.txt
cellpyability-0.1.0.dist-info/top_level.txt
cellpyability-0.1.0.dist-info/RECORD
