Metadata-Version: 2.4
Name: cellpyability
Version: 0.1.0
Summary: Open-source cell viability and dose-response analysis tool
Author-email: James Elia <james.elia@yale.edu>
Maintainer-email: James Elia <james.elia@yale.edu>
License: MIT License
Project-URL: Homepage, https://github.com/bindralab/CellPyAbility
Project-URL: Repository, https://github.com/bindralab/CellPyAbility
Project-URL: Issues, https://github.com/bindralab/CellPyAbility/issues
Keywords: cell viability,dose-response,image analysis,drug screening,synergy
Classifier: Development Status :: 3 - Alpha
Classifier: Intended Audience :: Science/Research
Classifier: License :: OSI Approved :: MIT License
Classifier: Programming Language :: Python :: 3
Classifier: Programming Language :: Python :: 3.8
Classifier: Programming Language :: Python :: 3.9
Classifier: Programming Language :: Python :: 3.10
Classifier: Programming Language :: Python :: 3.11
Classifier: Programming Language :: Python :: 3.12
Classifier: Topic :: Scientific/Engineering :: Bio-Informatics
Classifier: Topic :: Scientific/Engineering :: Image Processing
Requires-Python: >=3.8
License-File: LICENSE.txt
Requires-Dist: matplotlib<4.0.0,>=3.5.0
Requires-Dist: numpy<2.0.0,>=1.24.4
Requires-Dist: pandas<3.0.0,>=2.0.0
Requires-Dist: plotly<6.0.0,>=5.0.0
Requires-Dist: scipy<2.0.0,>=1.10.0
Provides-Extra: dev
Requires-Dist: pytest>=7.0; extra == "dev"
Requires-Dist: pytest-cov>=4.0; extra == "dev"
Dynamic: license-file
